monsql/MonSQL.py
monsql/__init__.py
monsql_python-0.0.1.dist-info/LICENSE
monsql_python-0.0.1.dist-info/METADATA
monsql_python-0.0.1.dist-info/WHEEL
monsql_python-0.0.1.dist-info/top_level.txt
monsql_python-0.0.1.dist-info/RECORD
