Metadata-Version: 2.1
Name: monsql-python
Version: 0.0.1
Summary: French overlay for MySQL
Home-page: https://github.com/MaitreRenard/MonSQL-python
Author: Masterfox, 0xNinja, Apollo
Author-email: tom.mounet@pm.me
License: UNKNOWN
Platform: UNKNOWN
Classifier: Programming Language :: Python :: 3
Classifier: License :: OSI Approved :: GNU General Public License v3 (GPLv3)
Classifier: Operating System :: OS Independent
Requires-Python: >=3.6
Requires-Dist: mysql-connector-python
